{
  "$schema": "schema://living-narrative-engine/action.schema.json",
  "id": "positioning:turn_around",
  "name": "Turn Around",
  "description": "Turn the target around or have them face you again.",
  "targets": {
    "primary": {
      "scope": "positioning:close_actors_facing_each_other_or_behind_target",
      "placeholder": "target",
      "description": "Actor to turn around"
    }
  },
  "required_components": {
    "actor": ["positioning:closeness"]
  },
  "forbidden_components": {
    "actor": ["intimacy:kissing"]
  },
  "template": "turn {target} around",
  "prerequisites": [],
  "visual": {
    "backgroundColor": "#00796b",
    "textColor": "#ffffff",
    "hoverBackgroundColor": "#00695c",
    "hoverTextColor": "#ffffff"
  }
}
