{
  "$schema": "schema://living-narrative-engine/mod-manifest.schema.json",
  "id": "weapons",
  "version": "1.0.0",
  "name": "Weapons System",
  "description": "Firearms, ammunition, reloading, and shooting mechanics.",
  "actionPurpose": "Wield and use weapons in threatening or combat situations.",
  "actionConsiderWhen": "Threatening someone with a weapon, intimidating with firearms, or displaying armed aggression.",
  "author": "Living Narrative Engine",
  "gameVersion": "0.0.1",
  "dependencies": [
    {
      "id": "items-core",
      "version": "1.0.0"
    },
    {
      "id": "recovery-states",
      "version": "^1.0.0"
    },
    {
      "id": "physical-control-states",
      "version": "^1.0.0"
    },
    {
      "id": "hugging-states",
      "version": "^1.0.0"
    },
    {
      "id": "sex-states",
      "version": "^1.0.0"
    },
    {
      "id": "personal-space-states",
      "version": "^1.0.0"
    },
    {
      "id": "anatomy",
      "version": "1.0.0"
    },
    {
      "id": "performances-states",
      "version": "^1.0.0"
    },
    {
      "id": "skills",
      "version": "1.0.0"
    },
    {
      "id": "damage-types",
      "version": "1.0.0"
    },
    {
      "id": "bending-states",
      "version": "^1.0.0"
    },
    {
      "id": "item-handling-states",
      "version": "^1.0.0"
    },
    {
      "id": "inventory",
      "version": "^1.0.0"
    }
  ],
  "content": {
    "components": [
      "ammo_container.component.json",
      "ammunition.component.json",
      "firearm.component.json",
      "magazine.component.json",
      "weapon.component.json"
    ],
    "macros": [
      "handleMeleeCritical.macro.json",
      "handleMeleeFumble.macro.json",
      "handleMeleeHit.macro.json",
      "handleMeleeMiss.macro.json"
    ],
    "scopes": [
      "grabbable_weapons_at_location.scope",
      "grabbable_weapons_in_inventory.scope",
      "weapons_in_inventory.scope",
      "wielded_blunt_weapons.scope",
      "wielded_cutting_weapons.scope",
      "wielded_piercing_weapons.scope"
    ],
    "conditions": [
      "event-is-action-quickly-wield-weapon.condition.json",
      "event-is-action-strike-target.condition.json",
      "event-is-action-swing-at-target.condition.json",
      "event-is-action-thrust-at-target.condition.json",
      "event-is-action-wield-threateningly.condition.json"
    ],
    "actions": [
      "quickly_wield_weapon.action.json",
      "strike_target.action.json",
      "swing_at_target.action.json",
      "thrust_at_target.action.json",
      "wield_threateningly.action.json"
    ],
    "rules": [
      "handle_quickly_wield_weapon.rule.json",
      "handle_strike_target.rule.json",
      "handle_swing_at_target.rule.json",
      "handle_thrust_at_target.rule.json",
      "handle_wield_threateningly.rule.json"
    ],
    "entities": {
      "definitions": [],
      "instances": []
    },
    "events": []
  }
}
