{
  "$schema": "schema://living-narrative-engine/entity-definition.schema.json",
  "id": "anatomy-creatures:beak",
  "description": "Titanic crushing beak of a kraken",
  "components": {
    "anatomy:part": {
      "subType": "beak",
      "hit_probability_weight": 2,
      "health_calculation_weight": 1
    },
    "anatomy:part_health": {
      "currentHealth": 35,
      "maxHealth": 35,
      "state": "healthy"
    },
    "core:name": {
      "text": "beak"
    },
    "core:weight": {
      "weight": 5
    },
    "descriptors:color_extended": {
      "color": "charcoal-gray"
    },
    "descriptors:shape_general": {
      "shape": "conical"
    },
    "descriptors:size_category": {
      "size": "large"
    },
    "descriptors:texture": {
      "texture": "ridged"
    },
    "damage-types:damage_capabilities": {
      "entries": [
        {
          "name": "piercing",
          "amount": 15,
          "penetration": 0.5,
          "bleed": {
            "enabled": true,
            "severity": "minor",
            "baseDurationTurns": 2
          }
        }
      ]
    }
  }
}
