{
  "$schema": "schema://living-narrative-engine/anatomy.blueprint.schema.json",
  "id": "dredgers:toad_folk_male",
  "root": "dredgers:toad_folk_male_torso",
  "compose": [
    {
      "part": "dredgers:amphibian_core",
      "include": ["slots", "clothingSlotMappings"]
    }
  ],
  "slots": {
    "penis": {
      "socket": "penis",
      "requirements": {
        "partType": "penis",
        "components": ["anatomy:part"]
      }
    },
    "left_testicle": {
      "socket": "left_testicle",
      "requirements": {
        "partType": "testicle",
        "components": ["anatomy:part"]
      }
    },
    "right_testicle": {
      "socket": "right_testicle",
      "requirements": {
        "partType": "testicle",
        "components": ["anatomy:part"]
      }
    }
  },
  "clothingSlotMappings": {
    "back_accessory": {
      "anatomySockets": ["upper_back", "lower_back"],
      "allowedLayers": ["accessories", "armor"]
    },
    "torso_lower": {
      "anatomySockets": [
        "left_hip",
        "right_hip",
        "penis",
        "left_testicle",
        "right_testicle",
        "asshole",
        "left_ass",
        "right_ass"
      ],
      "allowedLayers": ["underwear", "base", "outer"]
    },
    "full_body": {
      "blueprintSlots": ["head", "left_arm", "right_arm", "left_leg", "right_leg"],
      "allowedLayers": ["outer"]
    },
    "torso_upper": {
      "blueprintSlots": ["torso"],
      "allowedLayers": ["underwear", "base", "outer", "armor"]
    },
    "legs": {
      "blueprintSlots": ["left_leg", "right_leg"],
      "allowedLayers": ["base", "outer"]
    },
    "left_arm_clothing": {
      "blueprintSlots": ["left_arm"],
      "allowedLayers": ["base", "outer"]
    },
    "right_arm_clothing": {
      "blueprintSlots": ["right_arm"],
      "allowedLayers": ["base", "outer"]
    },
    "feet": {
      "blueprintSlots": ["left_foot", "right_foot"],
      "allowedLayers": ["base", "outer"]
    }
  }
}
