{
  "$schema": "schema://living-narrative-engine/component.schema.json",
  "id": "descriptors:body_composition",
  "description": "Describes body fat levels and overall body composition",
  "dataSchema": {
    "type": "object",
    "properties": {
      "composition": {
        "type": "string",
        "description": "The body composition type",
        "enum": [
          "underweight",
          "lean",
          "average",
          "soft",
          "chubby",
          "overweight",
          "obese",
          "atrophied",
          "emaciated",
          "skeletal",
          "malnourished",
          "dehydrated",
          "wasted",
          "desiccated",
          "bloated",
          "rotting"
        ],
        "default": "average"
      }
    },
    "required": ["composition"],
    "additionalProperties": false
  },
  "validationRules": {
    "generateValidator": true,
    "errorMessages": {
      "invalidEnum": "Invalid composition: {{value}}. Valid options: {{validValues}}",
      "missingRequired": "Composition is required",
      "invalidType": "Invalid type for composition: expected {{expected}}, got {{actual}}"
    },
    "suggestions": {
      "enableSimilarity": true,
      "maxDistance": 3,
      "maxSuggestions": 3
    }
  }
}
