{
  "$schema": "schema://living-narrative-engine/entity-definition.schema.json",
  "id": "anatomy:eldritch_speaking_orifice",
  "description": "Specialized mouth capable of producing maddening speech",
  "components": {
    "anatomy:part": {
      "subType": "eldritch_mouth",
      "hit_probability_weight": 4
    },
    "anatomy:part_health": {
      "currentHealth": 15,
      "maxHealth": 15,
      "state": "healthy"
    },
    "core:name": {
      "text": "speaking orifice"
    },
    "descriptors:texture": {
      "texture": "lipless-slit"
    },
    "descriptors:size_category": {
      "size": "small"
    },
    "descriptors:vocal_capability": {
      "capability": "ancient-languages"
    },
    "descriptors:effect": {
      "effect": "maddening-sounds"
    },
    "items:weight": {
      "weight": 1
    }
  }
}
