{
    "$schema": "http://example.com/schemas/world.schema.json",
    "id": "dredgers:dredgers",
    "name": "Corrupted plug in Eira Quenreach's estate",
    "description": "A self-contained game world centered around a corrupted plug in a noble's estate",
    "instances": [
        {
            "instanceId": "dredgers:canal_vestibule_instance"
        },
        {
            "instanceId": "dredgers:concordance_salon_instance"
        },
        {
            "instanceId": "dredgers:keyring_instance"
        },
        {
            "instanceId": "dredgers:pencil_instance"
        },
        {
            "instanceId": "dredgers:quill_instance"
        },
        {
            "instanceId": "dredgers:plain_notebook_instance"
        },
        {
            "instanceId": "dredgers:salvage_quarantine_undertaking_instance"
        },
        {
            "instanceId": "dredgers:concordance_salon_armchair_1_instance"
        },
        {
            "instanceId": "dredgers:concordance_salon_armchair_2_instance"
        },
        {
            "instanceId": "dredgers:concordance_salon_armchair_3_instance"
        },
        {
            "instanceId": "dredgers:concordance_salon_coffee_table_instance"
        },
        {
            "instanceId": "dredgers:jorren_weir_instance"
        },
        {
            "instanceId": "dredgers:kestrel_brune_instance"
        },
        {
            "instanceId": "dredgers:eira_quenreach_instance"
        },
        {
            "instanceId": "dredgers:cress_siltwell_instance"
        }
    ]
}