{
  "$schema": "schema://living-narrative-engine/anatomy.recipe.schema.json",
  "recipeId": "dredgers:toad_folk_male_standard",
  "blueprintId": "anatomy-creatures:toad_folk_male",
  "bodyDescriptors": {
    "height": "average",
    "skinColor": "olive",
    "build": "stocky",
    "composition": "bumpy",
    "hairDensity": "hairless",
    "smell": "earthy"
  },
  "slots": {
    "torso": {
      "partType": "torso",
      "preferId": "anatomy-creatures:toad_folk_male_torso"
    },
    "head": {
      "partType": "head",
      "preferId": "anatomy:humanoid_head"
    },
    "left_eye": {
      "partType": "eye",
      "preferId": "anatomy-creatures:toad_eye"
    },
    "right_eye": {
      "partType": "eye",
      "preferId": "anatomy-creatures:toad_eye"
    },
    "left_ear": {
      "partType": "ear",
      "preferId": "anatomy-creatures:toad_tympanum"
    },
    "right_ear": {
      "partType": "ear",
      "preferId": "anatomy-creatures:toad_tympanum"
    },
    "nose": {
      "partType": "nose",
      "preferId": "anatomy:humanoid_nose"
    },
    "mouth": {
      "partType": "mouth",
      "preferId": "anatomy:humanoid_mouth"
    },
    "teeth": {
      "partType": "teeth",
      "preferId": "anatomy:humanoid_teeth"
    },
    "left_arm": {
      "partType": "arm",
      "preferId": "anatomy:humanoid_arm"
    },
    "right_arm": {
      "partType": "arm",
      "preferId": "anatomy:humanoid_arm"
    },
    "left_hand": {
      "partType": "hand",
      "preferId": "anatomy:human_hand"
    },
    "right_hand": {
      "partType": "hand",
      "preferId": "anatomy:human_hand"
    },
    "left_leg": {
      "partType": "leg",
      "preferId": "anatomy:human_leg"
    },
    "right_leg": {
      "partType": "leg",
      "preferId": "anatomy:human_leg"
    },
    "left_foot": {
      "partType": "foot",
      "preferId": "anatomy:human_foot"
    },
    "right_foot": {
      "partType": "foot",
      "preferId": "anatomy:human_foot"
    },
    "penis": {
      "partType": "penis",
      "preferId": "anatomy:human_penis"
    },
    "left_testicle": {
      "partType": "testicle",
      "preferId": "anatomy:human_testicle"
    },
    "right_testicle": {
      "partType": "testicle",
      "preferId": "anatomy:human_testicle"
    },
    "asshole": {
      "partType": "asshole",
      "preferId": "anatomy:human_asshole"
    },
    "left_ass": {
      "partType": "ass_cheek",
      "preferId": "anatomy:human_ass_cheek"
    },
    "right_ass": {
      "partType": "ass_cheek",
      "preferId": "anatomy:human_ass_cheek"
    },
    "heart": {
      "partType": "heart",
      "preferId": "anatomy:human_heart"
    },
    "spine": {
      "partType": "spine",
      "preferId": "anatomy:human_spine"
    },
    "brain": {
      "partType": "brain",
      "preferId": "anatomy:human_brain"
    }
  }
}
