{
  "$schema": "http://example.com/schemas/entity-definition.schema.json",
  "id": "clothing:sneakers",
  "description": "Comfortable athletic sneakers for everyday wear",
  "components": {
    "clothing:wearable": {
      "layer": "base",
      "size": "m",
      "material": "synthetic",
      "equipmentSlots": {
        "primary": "feet_clothing"
      }
    },
    "core:name": {
      "text": "sneakers"
    },
    "core:description": {
      "text": "Comfortable athletic sneakers with good support"
    }
  }
}
